binance_data_exporter/__init__.py
binance_data_exporter/binance_data_exporter.py
binance_data_exporter-0.2.7.dist-info/METADATA
binance_data_exporter-0.2.7.dist-info/WHEEL
binance_data_exporter-0.2.7.dist-info/entry_points.txt
binance_data_exporter-0.2.7.dist-info/top_level.txt
binance_data_exporter-0.2.7.dist-info/RECORD
