Metadata-Version: 2.1
Name: binance-data-exporter
Version: 0.2.7
Summary: A tool for exporting in JSON the historical data of a symbol from Binance
Author: zestones
Author-email: idrissbenguezzou@gmail.com
Requires-Dist: requests
Requires-Dist: colorama
Requires-Dist: tabulate
